XieyiSenlinVamei/README.md
XieyiSenlinVamei/__init__.py
XieyiSenlinVamei/__main__.py
XieyiSenlinVamei/file.epub
XieyiSenlinVamei/index.html
XieyiSenlinVamei/css/__init__.py
XieyiSenlinVamei/css/annotations.css
XieyiSenlinVamei/css/main.css
XieyiSenlinVamei/css/normalize.css
XieyiSenlinVamei/css/popup.css
XieyiSenlinVamei/font/__init__.py
XieyiSenlinVamei/font/fontello.eot
XieyiSenlinVamei/font/fontello.svg
XieyiSenlinVamei/font/fontello.ttf
XieyiSenlinVamei/font/fontello.woff
XieyiSenlinVamei/img/__init__.py
XieyiSenlinVamei/img/annotator-glyph-sprite.png
XieyiSenlinVamei/img/annotator-icon-sprite.png
XieyiSenlinVamei/img/apple-touch-icon.png
XieyiSenlinVamei/img/cancelfullscreen.png
XieyiSenlinVamei/img/close.png
XieyiSenlinVamei/img/fullscreen.png
XieyiSenlinVamei/img/loader.gif
XieyiSenlinVamei/img/menu-icon.png
XieyiSenlinVamei/img/save.png
XieyiSenlinVamei/img/saved.png
XieyiSenlinVamei/img/settings-s.png
XieyiSenlinVamei/img/settings.png
XieyiSenlinVamei/img/star.png
XieyiSenlinVamei/js/__init__.py
XieyiSenlinVamei/js/epub.js
XieyiSenlinVamei/js/epub.min.js
XieyiSenlinVamei/js/epub.min.map
XieyiSenlinVamei/js/hooks.min.js
XieyiSenlinVamei/js/hooks.min.map
XieyiSenlinVamei/js/reader.js
XieyiSenlinVamei/js/reader.js.map
XieyiSenlinVamei/js/reader.min.js
XieyiSenlinVamei/js/reader.min.map
XieyiSenlinVamei/js/hooks/__init__.py
XieyiSenlinVamei/js/hooks/extensions/__init__.py
XieyiSenlinVamei/js/hooks/extensions/highlight.js
XieyiSenlinVamei/js/libs/__init__.py
XieyiSenlinVamei/js/libs/jquery.min.js
XieyiSenlinVamei/js/libs/localforage.min.js
XieyiSenlinVamei/js/libs/screenfull.js
XieyiSenlinVamei/js/libs/screenfull.min.js
XieyiSenlinVamei/js/libs/zip.min.js
XieyiSenlinVamei/js/plugins/__init__.py
XieyiSenlinVamei/js/plugins/hypothesis.js
XieyiSenlinVamei/js/plugins/search.js
xieyi_senlin_vamei-2024.2.29.0.dist-info/METADATA
xieyi_senlin_vamei-2024.2.29.0.dist-info/WHEEL
xieyi_senlin_vamei-2024.2.29.0.dist-info/entry_points.txt
xieyi_senlin_vamei-2024.2.29.0.dist-info/top_level.txt
xieyi_senlin_vamei-2024.2.29.0.dist-info/RECORD
